cryoheatflow/__init__.py
cryoheatflow/area.py
cryoheatflow/conductivity.py
cryoheatflow/emissivity.py
cryoheatflow/thermal.py
cryoheatflow-1.0.0.dist-info/licenses/LICENSE.md
cryoheatflow-1.0.0.dist-info/METADATA
cryoheatflow-1.0.0.dist-info/WHEEL
cryoheatflow-1.0.0.dist-info/top_level.txt
cryoheatflow-1.0.0.dist-info/RECORD
