Metadata-Version: 2.4
Name: cryoheatflow
Version: 1.0.0
Summary: Cryogenic thermal calculations library for cryostat design
Author-email: Adam McCaughan <adam.mccaughan@nist.gov>, Ryan Morgenstern <ryan.morgenstern@nist.gov>
License-Expression: GPL-3.0-or-later
Requires-Python: >=3
License-File: LICENSE.md
Requires-Dist: numpy
Requires-Dist: scipy
Dynamic: license-file
